register_8_bits/flipflop_d.vhd
library ieee;
use ieee.std_logic_1164.all;

entity flipflop_d is
    port (
        D     : in  std_logic;   -- Entrada de dados
        Clk   : in  std_logic;   -- Entrada de clock
        Q     : out std_logic;   -- Saída Q
        Q_n   : out std_logic    -- Saída Q' (complemento)
    );
end entity flipflop_d;

architecture behavioral of flipflop_d is
    signal Q_internal : std_logic := '0';
begin
    
    -- Processo para o flip-flop D
    process(Clk)
    begin
        if rising_edge(Clk) then
            Q <= D;
            Q_n <= not D;
        end if;
    end process;
    
end architecture behavioral;

register_8_bits/register_8bit.vhd
library ieee;
use ieee.std_logic_1164.all;

entity register_8bit is
    port (
        D     : in  std_logic_vector(7 downto 0);  -- Dados de entrada paralelos (8 bits)
        Clk   : in  std_logic;                     -- Clock comum para todos os flip-flops
        Q     : out std_logic_vector(7 downto 0);  -- Saídas Q (8 bits)
        Q_n   : out std_logic_vector(7 downto 0)   -- Saídas Q' (8 bits)
    );
end entity register_8bit;

architecture structural of register_8bit is
    
    -- Declaração do componente flip-flop D
    component flipflop_d
        port (
            D     : in  std_logic;
            Clk   : in  std_logic;
            Q     : out std_logic;
            Q_n   : out std_logic
        );
    end component;
    
begin
    
    -- Instanciação de 8 flip-flops D
    -- Cada bit do registrador é implementado com um flip-flop D
    
    FF0: flipflop_d port map (
        D   => D(0),
        Clk => Clk,
        Q   => Q(0),
        Q_n => Q_n(0)
    );
    
    FF1: flipflop_d port map (
        D   => D(1),
        Clk => Clk,
        Q   => Q(1),
        Q_n => Q_n(1)
    );
    
    FF2: flipflop_d port map (
        D   => D(2),
        Clk => Clk,
        Q   => Q(2),
        Q_n => Q_n(2)
    );
    
    FF3: flipflop_d port map (
        D   => D(3),
        Clk => Clk,
        Q   => Q(3),
        Q_n => Q_n(3)
    );
    
    FF4: flipflop_d port map (
        D   => D(4),
        Clk => Clk,
        Q   => Q(4),
        Q_n => Q_n(4)
    );
    
    FF5: flipflop_d port map (
        D   => D(5),
        Clk => Clk,
        Q   => Q(5),
        Q_n => Q_n(5)
    );
    
    FF6: flipflop_d port map (
        D   => D(6),
        Clk => Clk,
        Q   => Q(6),
        Q_n => Q_n(6)
    );
    
    FF7: flipflop_d port map (
        D   => D(7),
        Clk => Clk,
        Q   => Q(7),
        Q_n => Q_n(7)
    );
    
end architecture structural;

register_8_bits/tb_register_8bit.vhd
library ieee;
use ieee.std_logic_1164.all;
use ieee.numeric_std.all;

entity tb_register_8bit is
end entity tb_register_8bit;

architecture sim of tb_register_8bit is
    
    -- Sinais para conectar ao registrador
    signal clk  : std_logic := '0';
    signal D    : std_logic_vector(7 downto 0) := (others => '0');
    signal Q    : std_logic_vector(7 downto 0);
    signal Q_n  : std_logic_vector(7 downto 0);
    
    -- Declaração do componente registrador
    component register_8bit
        port (
            D     : in  std_logic_vector(7 downto 0);
            Clk   : in  std_logic;
            Q     : out std_logic_vector(7 downto 0);
            Q_n   : out std_logic_vector(7 downto 0)
        );
    end component;
    
    -- Constante para período do clock
    constant clk_period : time := 20 ns;
    
begin
    
    -- Instanciação do registrador sob teste
    uut: register_8bit port map (
        D   => D,
        Clk => clk,
        Q   => Q,
        Q_n => Q_n
    );
    
    -- Processo para geração do clock
    clk_process: process
    begin
        while now < 220 ns loop
            clk <= '1';
            wait for clk_period/2;
            clk <= '0';
            wait for clk_period/2;
        end loop;
        wait;
    end process;
    
    -- Processo de estimulos para testar o registrador
    stimulus_process: process
    begin
        -- Aguardar um pouco antes de iniciar os testes
        -- wait for 10 ns;
        
        -- Teste 1: Carregar valor 00000000
        D <= "00000000";
        wait for clk_period;

        D <= "00000001";  -- 1
        wait for clk_period;
        
        D <= "00000010";  -- 2
        wait for clk_period;
        
        D <= "00000100";  -- 4
        wait for clk_period;
        
        D <= "00001000";  -- 8
        wait for clk_period;
        
        D <= "00010000";  -- 16
        wait for clk_period;
        
        D <= "00100000";  -- 32
        wait for clk_period;
        
        D <= "01000000";  -- 64
        wait for clk_period;
        
        D <= "10000000";  -- 128
        wait for clk_period;
        
        wait;
        
    end process;
   
    
end architecture sim;

register_8_bits/register_8bit_simulation.vcd
$date
  Sun Sep 21 14:30:44 2025
$end
$version
  GHDL v0
$end
$timescale
  1 fs
$end
$scope module standard $end
$upscope $end
$scope module std_logic_1164 $end
$upscope $end
$scope module numeric_std $end
$upscope $end
$scope module tb_register_8bit $end
$var reg 1 ! clk $end
$var reg 8 " d[7:0] $end
$var reg 8 # q[7:0] $end
$var reg 8 $ q_n[7:0] $end
$scope module uut $end
$var reg 8 % d[7:0] $end
$var reg 1 & clk $end
$var reg 8 ' q[7:0] $end
$var reg 8 ( q_n[7:0] $end
$scope module ff0 $end
$var reg 1 ) d $end
$var reg 1 * clk $end
$var reg 1 + q $end
$var reg 1 , q_n $end
$var reg 1 - q_internal $end
$upscope $end
$scope module ff1 $end
$var reg 1 . d $end
$var reg 1 / clk $end
$var reg 1 0 q $end
$var reg 1 1 q_n $end
$var reg 1 2 q_internal $end
$upscope $end
$scope module ff2 $end
$var reg 1 3 d $end
$var reg 1 4 clk $end
$var reg 1 5 q $end
$var reg 1 6 q_n $end
$var reg 1 7 q_internal $end
$upscope $end
$scope module ff3 $end
$var reg 1 8 d $end
$var reg 1 9 clk $end
$var reg 1 : q $end
$var reg 1 ; q_n $end
$var reg 1 < q_internal $end
$upscope $end
$scope module ff4 $end
$var reg 1 = d $end
$var reg 1 > clk $end
$var reg 1 ? q $end
$var reg 1 @ q_n $end
$var reg 1 A q_internal $end
$upscope $end
$scope module ff5 $end
$var reg 1 B d $end
$var reg 1 C clk $end
$var reg 1 D q $end
$var reg 1 E q_n $end
$var reg 1 F q_internal $end
$upscope $end
$scope module ff6 $end
$var reg 1 G d $end
$var reg 1 H clk $end
$var reg 1 I q $end
$var reg 1 J q_n $end
$var reg 1 K q_internal $end
$upscope $end
$scope module ff7 $end
$var reg 1 L d $end
$var reg 1 M clk $end
$var reg 1 N q $end
$var reg 1 O q_n $end
$var reg 1 P q_internal $end
$upscope $end
$upscope $end
$upscope $end
$enddefinitions $end
#0
1!
b00000000 "
b00000000 #
b11111111 $
b00000000 %
1&
b00000000 '
b11111111 (
0)
1*
0+
1,
0-
0.
1/
00
11
02
03
14
05
16
07
08
19
0:
1;
0<
0=
1>
0?
1@
0A
0B
1C
0D
1E
0F
0G
1H
0I
1J
0K
0L
1M
0N
1O
0P
#10000000
0!
0&
0*
0/
04
09
0>
0C
0H
0M
#20000000
1!
b00000001 "
b00000001 #
b11111110 $
b00000001 %
1&
b00000001 '
b11111110 (
1)
1*
1+
0,
1/
14
19
1>
1C
1H
1M
#30000000
0!
0&
0*
0/
04
09
0>
0C
0H
0M
#40000000
1!
b00000010 "
b00000010 #
b11111101 $
b00000010 %
1&
b00000010 '
b11111101 (
0)
1*
0+
1,
1.
1/
10
01
14
19
1>
1C
1H
1M
#50000000
0!
0&
0*
0/
04
09
0>
0C
0H
0M
#60000000
1!
b00000100 "
b00000100 #
b11111011 $
b00000100 %
1&
b00000100 '
b11111011 (
1*
0.
1/
00
11
13
14
15
06
19
1>
1C
1H
1M
#70000000
0!
0&
0*
0/
04
09
0>
0C
0H
0M
#80000000
1!
b00001000 "
b00001000 #
b11110111 $
b00001000 %
1&
b00001000 '
b11110111 (
1*
1/
03
14
05
16
18
19
1:
0;
1>
1C
1H
1M
#90000000
0!
0&
0*
0/
04
09
0>
0C
0H
0M
#100000000
1!
b00010000 "
b00010000 #
b11101111 $
b00010000 %
1&
b00010000 '
b11101111 (
1*
1/
14
08
19
0:
1;
1=
1>
1?
0@
1C
1H
1M
#110000000
0!
0&
0*
0/
04
09
0>
0C
0H
0M
#120000000
1!
b00100000 "
b00100000 #
b11011111 $
b00100000 %
1&
b00100000 '
b11011111 (
1*
1/
14
19
0=
1>
0?
1@
1B
1C
1D
0E
1H
1M
#130000000
0!
0&
0*
0/
04
09
0>
0C
0H
0M
#140000000
1!
b01000000 "
b01000000 #
b10111111 $
b01000000 %
1&
b01000000 '
b10111111 (
1*
1/
14
19
1>
0B
1C
0D
1E
1G
1H
1I
0J
1M
#150000000
0!
0&
0*
0/
04
09
0>
0C
0H
0M
#160000000
1!
b10000000 "
b10000000 #
b01111111 $
b10000000 %
1&
b10000000 '
b01111111 (
1*
1/
14
19
1>
1C
0G
1H
0I
1J
1L
1M
1N
0O
