unid6_cap1/state_machine.vhd
library ieee;
use ieee.std_logic_1164.all;
use ieee.numeric_std.all;

entity state_machine is
  port (
    clk   : in std_logic;  -- clock do sistema
    rst_n : in std_logic;  -- reset assíncrono ativo-baixo
    sensor : in std_logic;  -- detecta presença (1 = pessoa detectada)
    fechar_manual : in std_logic;  -- botão de fechamento antecipado
    fim_curso_aberta : in std_logic;  -- sensor indica porta totalmente aberta
    fim_curso_fechada : in std_logic;  -- sensor indica porta totalmente fechada
    motor_abrir      : out std_logic;  -- ativa o motor no sentido de abrir
    motor_fechar     : out std_logic   -- ativa o motor no sentido de fechar
  );
end entity;

architecture rtl of state_machine is
-- begin

  type state_type is (FECHADA, ABRINDO, ABERTA, FECHANDO);
  signal state, next_state : state_type;
  constant T_ABERTA_MAX : integer := 6;  -- contador maior
  signal timer_cnt : integer range 0 to 6 := 0;
  
begin
    process(clk, rst_n)
    begin
      if rst_n = '0' then
        state <= FECHADA;
        timer_cnt <= 0;
      elsif rising_edge(clk) then
        state <= next_state;

        -- temporizador de 4 bits para estado ABERTA
        if state = ABERTA then
        -- Durante ABERTA, se sensor=1, reinicia temporizador
          if sensor = '1' then
            timer_cnt <= 0;  -- reinicia enquanto há presença
          elsif timer_cnt < T_ABERTA_MAX then
            timer_cnt <= timer_cnt + 1;
          end if;
        else
          timer_cnt <= timer_cnt + 1;  
        end if;
      end if;

    end process;

    process(state, sensor, fechar_manual, fim_curso_aberta, fim_curso_fechada, timer_cnt)
    begin
        -- valores padrão
        next_state   <= state;
        motor_abrir  <= '0';
        motor_fechar <= '0';

        case state is
            
            ----------------------------------------------------------------
            when FECHADA =>
              -- Estado: FECHADA — porta fechada, motores desligados
              -- Transição: FECHADA → ABRINDO quando sensor=1
              motor_abrir  <= '0';
              motor_fechar <= '0';
              if sensor = '1' then
                next_state <= ABRINDO;
              end if;

            ----------------------------------------------------------------
            when ABRINDO =>
              -- Estado: ABRINDO — motor_abrir ligado até porta abrir completamente
              -- Transição: ABRINDO → ABERTA quando fim_curso_aberta=1
              motor_abrir  <= '1';
              motor_fechar <= '0';
              if fim_curso_aberta = '1' then
                next_state <= ABERTA;
              end if;

            ----------------------------------------------------------------
            when ABERTA =>
              -- Estado: ABERTA — porta aberta, aguarda tempo T_ABERTA sem presença
              -- Transição: ABERTA → FECHANDO quando T_ABERTA expira e sensor=0, ou fechar_manual=1

              motor_abrir  <= '0';
              motor_fechar <= '0';
              
              if (timer_cnt >= T_ABERTA_MAX and sensor = '0') or(fechar_manual = '1') then
                next_state <= FECHANDO;
              end if;
 
            ----------------------------------------------------------------
            when FECHANDO =>
              -- Estado: FECHANDO — motor_fechar ligado até porta fechar completamente
              -- Transição: FECHANDO → FECHADA quando fim_curso_fechada=1

              motor_abrir  <= '0';
              motor_fechar <= '1';
              if fim_curso_fechada = '1' then
                next_state <= FECHADA;
              end if;

            ----------------------------------------------------------------
            when others =>
              next_state   <= FECHADA;
              motor_abrir  <= '0';
              motor_fechar <= '0';
        end case;
    end process;

end rtl;

unid6_cap1/tb_state_machine.vhd
library ieee;
use ieee.std_logic_1164.all;

entity tb_state_machine is
end;

architecture sim of tb_state_machine is
   -- sinais de estímulo
  signal clk              : std_logic := '0';
  signal rst_n            : std_logic := '0';
  signal sensor           : std_logic := '0';
  signal fechar_manual    : std_logic := '0';
  signal fim_curso_aberta : std_logic := '0';
  signal fim_curso_fechada: std_logic := '1';

  -- saídas do DUT
  signal motor_abrir      : std_logic;
  signal motor_fechar     : std_logic;

begin
  DUT: entity work.state_machine
    port map (
      clk              => clk,
      rst_n            => rst_n,
      sensor           => sensor,
      fechar_manual    => fechar_manual,
      fim_curso_aberta => fim_curso_aberta,
      fim_curso_fechada=> fim_curso_fechada,
      motor_abrir      => motor_abrir,
      motor_fechar     => motor_fechar
    );


  clk <= not clk after 10 ns;

  stim_proc: process
  begin
    -- Reset inicial
    rst_n <= '0';
    wait for 30 ns;
    rst_n <= '1';
    wait for 30 ns;

    -- Pessoa detectada => porta começa a abrir
    sensor <= '1';
    wait for 30 ns;
    
    -- Simula porta saindo da posição fechada
    fim_curso_fechada <= '0';
    wait for 30 ns;

    -- Porta chegou no fim de curso aberta
    fim_curso_aberta <= '1';
    wait for 30 ns;

    -- Pessoa sai => porta fecha
    sensor <= '0';
    wait for 30 ns;
    
    -- Simula porta saindo da posição aberta
    fim_curso_aberta <= '0';
    wait for 30 ns;
    
    -- Porta voltou ao fim de curso fechada
    fim_curso_fechada <= '1';
    wait for 30 ns;

    -- Novo ciclo: presença novamente
    sensor <= '1';
    wait for 30 ns;
    fim_curso_fechada <= '0';
    wait for 30 ns;
    fim_curso_aberta <= '1';
    wait for 30 ns;

    -- Fechamento manual
    fechar_manual <= '1'; 
    wait for 30 ns;
    fechar_manual <= '0';
    fim_curso_aberta <= '0';
    wait for 30 ns;
    fim_curso_fechada <= '1';
    wait for 30 ns;

    wait;
  end process;
end architecture;

unid6_cap1/state_machine.vcd
$date
  Sun Oct 05 22:26:02 2025
$end
$version
  GHDL v0
$end
$timescale
  1 fs
$end
$scope module standard $end
$upscope $end
$scope module std_logic_1164 $end
$upscope $end
$scope module numeric_std $end
$upscope $end
$scope module tb_state_machine $end
$var reg 1 ! clk $end
$var reg 1 " rst_n $end
$var reg 1 # sensor $end
$var reg 1 $ fechar_manual $end
$var reg 1 % fim_curso_aberta $end
$var reg 1 & fim_curso_fechada $end
$var reg 1 ' motor_abrir $end
$var reg 1 ( motor_fechar $end
$scope module dut $end
$var reg 1 ) clk $end
$var reg 1 * rst_n $end
$var reg 1 + sensor $end
$var reg 1 , fechar_manual $end
$var reg 1 - fim_curso_aberta $end
$var reg 1 . fim_curso_fechada $end
$var reg 1 / motor_abrir $end
$var reg 1 0 motor_fechar $end
$comment state is not handled $end
$comment next_state is not handled $end
$var integer 32 1 timer_cnt $end
$upscope $end
$upscope $end
$enddefinitions $end
#0
0!
0"
0#
0$
0%
1&
0'
0(
0)
0*
0+
0,
0-
1.
0/
00
b0 1
#10000000
1!
1)
#20000000
0!
0)
#30000000
1!
1"
1)
1*
#40000000
0!
0)
#50000000
1!
1)
b1 1
#60000000
0!
1#
0)
1+
#70000000
1!
1'
1)
1/
b10 1
#80000000
0!
0)
#90000000
1!
0&
1)
0.
1/
b11 1
#100000000
0!
0)
#110000000
1!
1)
1/
b100 1
#120000000
0!
1%
0)
1-
1/
#130000000
1!
0'
1)
0/
b101 1
#140000000
0!
0)
#150000000
1!
0#
1)
0+
b0 1
#160000000
0!
0)
#170000000
1!
1)
b1 1
#180000000
0!
0%
0)
0-
#190000000
1!
1)
b10 1
#200000000
0!
0)
#210000000
1!
1&
1)
1.
b11 1
#220000000
0!
0)
#230000000
1!
1)
b100 1
#240000000
0!
1#
0)
1+
#250000000
1!
1)
b0 1
#260000000
0!
0)
#270000000
1!
0&
1)
0.
#280000000
0!
0)
#290000000
1!
1)
#300000000
0!
1%
0)
1-
#310000000
1!
1)
#320000000
0!
0)
#330000000
1!
1$
1)
1,
#340000000
0!
0)
#350000000
1!
1(
1)
10
#360000000
0!
0$
0%
0)
0,
0-
10
#370000000
1!
1)
10
b1 1
#380000000
0!
0)
#390000000
1!
1&
1)
1.
10
b10 1
#400000000
0!
0)
#410000000
1!
0(
1)
00
b11 1
#420000000
0!
0)
#430000000
1!
1'
1)
1/
b100 1
#440000000
0!
0)
#450000000
1!
1)
1/
b101 1
#460000000
0!
0)
#470000000
1!
1)
1/
b110 1
