food_light/light.vhd
library ieee;
use ieee.std_logic_1164.all;

entity light is
    port (
        Clk     : in  std_logic;
        A       : in  std_logic;                     
        B       : in  std_logic;                     
        C       : in  std_logic;
        D       : in  std_logic;
        -- Saída da função booleana S = BCD + AC + AB
        S       : out std_logic
    );
end entity;

architecture behavioral of light is
begin

    process(Clk)
    begin
        if rising_edge(Clk) then
            S <= (B and C and D) or (A and C) or (A and B);
        end if;
    end process;
   

end behavioral;

food_light/tb_light.vhd
library ieee;
use ieee.std_logic_1164.all;

entity tb_light is
end entity;

architecture sim of tb_light is
  -- Sinais para testar a função booleana S = BCD + AC + AB
  signal Clk : std_logic := '0';
  signal A   : std_logic := '0';
  signal B   : std_logic := '0';
  signal C   : std_logic := '0';
  signal D   : std_logic := '0';
  signal S   : std_logic;

  component light
    port (
      Clk : in  std_logic;
      A   : in  std_logic;
      B   : in  std_logic;
      C   : in  std_logic;
      D   : in  std_logic;
      S   : out std_logic
    );
  end component;

begin

  -- Instância do componente para testar a função S = BCD + AC + AB
  uut: light port map(
    Clk => Clk,
    A   => A,
    B   => B,
    C   => C,
    D   => D,
    S   => S
  );

  -- Geração de clock: 10 ns de período
  clk_process: process
  begin
    while now < 320 ns loop
      Clk <= not Clk;
      wait for 20 ns;
    end loop;
    wait;
  end process;

  -- Processo de teste para todas as combinações de A, B, C e D
  stim_proc: process
  begin
    
    -- A=0, B=0, C=0, D=0 -> S deve ser 0
    A <= '0'; B <= '0'; C <= '0'; D <= '0';
    wait for 20 ns;
    
    -- A=0, B=0, C=0, D=1 -> S deve ser 0
    A <= '0'; B <= '0'; C <= '0'; D <= '1';
    wait for 20 ns;
    
    -- A=0, B=0, C=1, D=0 -> S deve ser 0
    A <= '0'; B <= '0'; C <= '1'; D <= '0';
    wait for 20 ns;
    
    -- A=0, B=0, C=1, D=1 -> S deve ser 0
    A <= '0'; B <= '0'; C <= '1'; D <= '1';
    wait for 20 ns;
    
    -- A=0, B=1, C=0, D=0 -> S deve ser 0
    A <= '0'; B <= '1'; C <= '0'; D <= '0';
    wait for 20 ns;

    -- A=0, B=1, C=0, D=1 -> S deve ser 0
    A <= '0'; B <= '1'; C <= '0'; D <= '1';
    wait for 20 ns;
    
    -- A=0, B=1, C=1, D=0 -> S deve ser 0
    A <= '0'; B <= '1'; C <= '1'; D <= '0';
    wait for 20 ns;
    
    -- A=0, B=1, C=1, D=1 -> S deve ser 1
    A <= '0'; B <= '1'; C <= '1'; D <= '1';
    wait for 20 ns;
    
    -- A=1, B=0, C=0, D=0 -> S deve ser 0
    A <= '1'; B <= '0'; C <= '0'; D <= '0';
    wait for 20 ns;
    
    -- A=0, B=0, C=0, D=1 -> S deve ser 0
    A <= '1'; B <= '0'; C <= '0'; D <= '1';
    wait for 20 ns;
    
    -- A=1, B=0, C=1, D=0 -> S deve ser 1
    A <= '1'; B <= '0'; C <= '1'; D <= '0';
    wait for 20 ns;
    
    -- A=1, B=0, C=1, D=1 -> S deve ser 1
    A <= '1'; B <= '0'; C <= '1'; D <= '1';
    wait for 20 ns;
    
    -- A=1, B=1, C=0, D=0 -> S deve ser 1
    A <= '1'; B <= '1'; C <= '0'; D <= '0';
    wait for 20 ns;
    
    -- A=1, B=1, C=0, D=1 -> S deve ser 1
    A <= '1'; B <= '1'; C <= '0'; D <= '1';
    wait for 20 ns;
    
    -- A=1, B=1, C=1, D=0 -> S deve ser 1
    A <= '1'; B <= '1'; C <= '1'; D <= '0';
    wait for 20 ns;
    
    -- A=1, B=1, C=1, D=1 -> S deve ser 1
    A <= '1'; B <= '1'; C <= '1'; D <= '1';
    wait for 20 ns;
    
    

    wait;
  end process;

end architecture;

food_light/light.vcd
$date
  Fri Sep 19 16:04:45 2025
$end
$version
  GHDL v0
$end
$timescale
  1 fs
$end
$scope module standard $end
$upscope $end
$scope module std_logic_1164 $end
$upscope $end
$scope module tb_light $end
$var reg 1 ! clk $end
$var reg 1 " a $end
$var reg 1 # b $end
$var reg 1 $ c $end
$var reg 1 % d $end
$var reg 1 & s $end
$scope module uut $end
$var reg 1 ' clk $end
$var reg 1 ( a $end
$var reg 1 ) b $end
$var reg 1 * c $end
$var reg 1 + d $end
$var reg 1 , s $end
$upscope $end
$upscope $end
$enddefinitions $end
#0
1!
0"
0#
0$
0%
0&
1'
0(
0)
0*
0+
0,
#20000000
0!
1%
0'
1+
#40000000
1!
1$
0%
1'
1*
0+
#60000000
0!
1%
0'
1+
#80000000
1!
1#
0$
0%
1'
1)
0*
0+
#100000000
0!
1%
0'
1+
#120000000
1!
1$
0%
1'
1*
0+
#140000000
0!
1%
0'
1+
#160000000
1!
1"
0#
0$
0%
1'
1(
0)
0*
0+
#180000000
0!
1%
0'
1+
#200000000
1!
1$
0%
1&
1'
1*
0+
1,
#220000000
0!
1%
0'
1+
#240000000
1!
1#
0$
0%
1'
1)
0*
0+
#260000000
0!
1%
0'
1+
#280000000
1!
1$
0%
1'
1*
0+
#300000000
0!
1%
0'
1+
